<?xml version="1.0"?>
<config urldb="paloaltonetworks" version="9.2.0">
  <mgt-config>
    <users>
      <entry name="admin">
        <phash>$1$crnraafg$yAn1oc.YNZDtVXMQ1IH24.</phash>
        <permissions>
          <role-based>
            <superuser>yes</superuser>
          </role-based>
        </permissions>
      </entry>
    </users>
  </mgt-config>
  <shared>
    <application/>
    <application-group/>
    <service/>
    <service-group/>
    <botnet>
      <configuration>
        <http>
          <dynamic-dns>
            <enabled>yes</enabled>
            <threshold>5</threshold>
          </dynamic-dns>
          <malware-sites>
            <enabled>yes</enabled>
            <threshold>5</threshold>
          </malware-sites>
          <recent-domains>
            <enabled>yes</enabled>
            <threshold>5</threshold>
          </recent-domains>
          <ip-domains>
            <enabled>yes</enabled>
            <threshold>10</threshold>
          </ip-domains>
          <executables-from-unknown-sites>
            <enabled>yes</enabled>
            <threshold>5</threshold>
          </executables-from-unknown-sites>
        </http>
        <other-applications>
          <irc>yes</irc>
        </other-applications>
        <unknown-applications>
          <unknown-tcp>
            <destinations-per-hour>10</destinations-per-hour>
            <sessions-per-hour>10</sessions-per-hour>
            <session-length>
              <maximum-bytes>100</maximum-bytes>
              <minimum-bytes>50</minimum-bytes>
            </session-length>
          </unknown-tcp>
          <unknown-udp>
            <destinations-per-hour>10</destinations-per-hour>
            <sessions-per-hour>10</sessions-per-hour>
            <session-length>
              <maximum-bytes>100</maximum-bytes>
              <minimum-bytes>50</minimum-bytes>
            </session-length>
          </unknown-udp>
        </unknown-applications>
      </configuration>
      <report>
        <topn>100</topn>
        <scheduled>yes</scheduled>
      </report>
    </botnet>
    <content-preview>
      <application/>
      <application-type>
        <category/>
        <technology/>
      </application-type>
    </content-preview>
    <certificate/>
    <ssl-tls-service-profile/>
    <server-profile>
      <ldap>
        <entry name="lab-active-directory">
          <server>
            <entry name="lab-client">
              <address>192.168.1.20</address>
              <port>389</port>
            </entry>
          </server>
          <ldap-type>active-directory</ldap-type>
          <bind-dn>lab-user-id@lab.local</bind-dn>
          <bind-password>-AQ==CaHEtj8wWUhMJjtCSo8m3cTNXm0=m2FUhEU5thOOOgEQzCV6Xw==</bind-password>
          <ssl>no</ssl>
          <base>DC=lab,DC=local</base>
        </entry>
      </ldap>
    </server-profile>
    <authentication-profile>
      <entry name="auth-gp">
        <multi-factor-auth>
          <mfa-enable>no</mfa-enable>
        </multi-factor-auth>
        <method>
          <ldap>
            <server-profile>lab-active-directory</server-profile>
          </ldap>
        </method>
        <allow-list>
          <member>all</member>
        </allow-list>
        <user-domain>lab.local</user-domain>
      </entry>
    </authentication-profile>
  </shared>
  <devices>
    <entry name="localhost.localdomain">
      <network>
        <interface>
          <ethernet>
            <entry name="ethernet1/2">
              <layer3>
                <ipv6>
                  <neighbor-discovery>
                    <router-advertisement>
                      <enable>no</enable>
                    </router-advertisement>
                  </neighbor-discovery>
                </ipv6>
                <ndp-proxy>
                  <enabled>no</enabled>
                </ndp-proxy>
                <ip>
                  <entry name="192.168.1.1/24"/>
                </ip>
                <interface-management-profile>ping-response-pages</interface-management-profile>
                <lldp>
                  <enable>no</enable>
                </lldp>
                <untagged-sub-interface>yes</untagged-sub-interface>
                <units>
                  <entry name="ethernet1/2.2">
                    <ipv6>
                      <neighbor-discovery>
                        <router-advertisement>
                          <enable>no</enable>
                        </router-advertisement>
                      </neighbor-discovery>
                    </ipv6>
                    <ndp-proxy>
                      <enabled>no</enabled>
                    </ndp-proxy>
                    <adjust-tcp-mss>
                      <enable>no</enable>
                    </adjust-tcp-mss>
                    <ip>
                      <entry name="192.168.2.1/24"/>
                    </ip>
                    <interface-management-profile>ping</interface-management-profile>
                    <comment>internal gateway</comment>
                  </entry>
                </units>
              </layer3>
              <comment>inside interface</comment>
            </entry>
            <entry name="ethernet1/3">
              <layer3>
                <ipv6>
                  <neighbor-discovery>
                    <router-advertisement>
                      <enable>no</enable>
                    </router-advertisement>
                  </neighbor-discovery>
                </ipv6>
                <ndp-proxy>
                  <enabled>no</enabled>
                </ndp-proxy>
                <ip>
                  <entry name="192.168.50.1/24"/>
                </ip>
                <interface-management-profile>ping-https-api</interface-management-profile>
                <lldp>
                  <enable>no</enable>
                </lldp>
              </layer3>
              <comment>extranet interface</comment>
            </entry>
            <entry name="ethernet1/1">
              <layer3>
                <ipv6>
                  <neighbor-discovery>
                    <router-advertisement>
                      <enable>no</enable>
                    </router-advertisement>
                  </neighbor-discovery>
                </ipv6>
                <ndp-proxy>
                  <enabled>no</enabled>
                </ndp-proxy>
                <lldp>
                  <enable>no</enable>
                </lldp>
                <ip>
                  <entry name="203.0.113.20/24"/>
                </ip>
                <interface-management-profile>ping</interface-management-profile>
              </layer3>
              <comment>outside interface</comment>
            </entry>
            <entry name="ethernet1/4">
              <comment>vWire danger</comment>
              <virtual-wire>
                <lldp>
                  <enable>no</enable>
                </lldp>
              </virtual-wire>
            </entry>
            <entry name="ethernet1/5">
              <comment>vWire danger</comment>
              <virtual-wire>
                <lldp>
                  <enable>no</enable>
                </lldp>
              </virtual-wire>
            </entry>
          </ethernet>
          <tunnel>
            <units>
              <entry name="tunnel.11"/>
              <entry name="tunnel.12">
                <interface-management-profile>ping</interface-management-profile>
                <comment>Tunnel to Extranet</comment>
              </entry>
            </units>
          </tunnel>
        </interface>
        <profiles>
          <monitor-profile>
            <entry name="default">
              <interval>3</interval>
              <threshold>5</threshold>
              <action>wait-recover</action>
            </entry>
          </monitor-profile>
          <interface-management-profile>
            <entry name="ping-response-pages">
              <ping>yes</ping>
              <response-pages>yes</response-pages>
            </entry>
            <entry name="ping">
              <ping>yes</ping>
            </entry>
            <entry name="ping-https-api">
              <https>yes</https>
              <ping>yes</ping>
            </entry>
          </interface-management-profile>
        </profiles>
        <ike>
          <crypto-profiles>
            <ike-crypto-profiles>
              <entry name="default">
                <encryption>
                  <member>aes-128-cbc</member>
                  <member>3des</member>
                </encryption>
                <hash>
                  <member>sha1</member>
                </hash>
                <dh-group>
                  <member>group2</member>
                </dh-group>
                <lifetime>
                  <hours>8</hours>
                </lifetime>
              </entry>
              <entry name="Suite-B-GCM-128">
                <encryption>
                  <member>aes-128-cbc</member>
                </encryption>
                <hash>
                  <member>sha256</member>
                </hash>
                <dh-group>
                  <member>group19</member>
                </dh-group>
                <lifetime>
                  <hours>8</hours>
                </lifetime>
              </entry>
              <entry name="Suite-B-GCM-256">
                <encryption>
                  <member>aes-256-cbc</member>
                </encryption>
                <hash>
                  <member>sha384</member>
                </hash>
                <dh-group>
                  <member>group20</member>
                </dh-group>
                <lifetime>
                  <hours>8</hours>
                </lifetime>
              </entry>
              <entry name="AES256-DH2-SHA2">
                <hash>
                  <member>sha256</member>
                </hash>
                <dh-group>
                  <member>group2</member>
                </dh-group>
                <encryption>
                  <member>aes-256-cbc</member>
                </encryption>
                <lifetime>
                  <hours>8</hours>
                </lifetime>
              </entry>
            </ike-crypto-profiles>
            <ipsec-crypto-profiles>
              <entry name="default">
                <esp>
                  <encryption>
                    <member>aes-128-cbc</member>
                    <member>3des</member>
                  </encryption>
                  <authentication>
                    <member>sha1</member>
                  </authentication>
                </esp>
                <dh-group>group2</dh-group>
                <lifetime>
                  <hours>1</hours>
                </lifetime>
              </entry>
              <entry name="Suite-B-GCM-128">
                <esp>
                  <encryption>
                    <member>aes-128-gcm</member>
                  </encryption>
                  <authentication>
                    <member>none</member>
                  </authentication>
                </esp>
                <dh-group>group19</dh-group>
                <lifetime>
                  <hours>1</hours>
                </lifetime>
              </entry>
              <entry name="Suite-B-GCM-256">
                <esp>
                  <encryption>
                    <member>aes-256-gcm</member>
                  </encryption>
                  <authentication>
                    <member>none</member>
                  </authentication>
                </esp>
                <dh-group>group20</dh-group>
                <lifetime>
                  <hours>1</hours>
                </lifetime>
              </entry>
              <entry name="AES256-SHA256">
                <esp>
                  <authentication>
                    <member>sha256</member>
                  </authentication>
                  <encryption>
                    <member>aes-256-cbc</member>
                  </encryption>
                </esp>
                <lifetime>
                  <hours>1</hours>
                </lifetime>
                <dh-group>group2</dh-group>
              </entry>
            </ipsec-crypto-profiles>
            <global-protect-app-crypto-profiles>
              <entry name="default">
                <encryption>
                  <member>aes-128-cbc</member>
                </encryption>
                <authentication>
                  <member>sha1</member>
                </authentication>
              </entry>
            </global-protect-app-crypto-profiles>
          </crypto-profiles>
          <gateway>
            <entry name="extranet-ike-gateway">
              <authentication>
                <pre-shared-key>
                  <key>-AQ==zPJb3ngM1sGjXlfX2+Qk6rbdv1I=ucInIpBmFcnkQK7zF4VO1w==</key>
                </pre-shared-key>
              </authentication>
              <protocol>
                <ikev1>
                  <dpd>
                    <enable>yes</enable>
                  </dpd>
                  <ike-crypto-profile>AES256-DH2-SHA2</ike-crypto-profile>
                </ikev1>
                <ikev2>
                  <dpd>
                    <enable>yes</enable>
                  </dpd>
                </ikev2>
              </protocol>
              <local-address>
                <ip>192.168.50.1/24</ip>
                <interface>ethernet1/3</interface>
              </local-address>
              <protocol-common>
                <nat-traversal>
                  <enable>no</enable>
                </nat-traversal>
                <fragmentation>
                  <enable>no</enable>
                </fragmentation>
              </protocol-common>
              <peer-address>
                <ip>192.168.50.10</ip>
              </peer-address>
            </entry>
          </gateway>
        </ike>
        <qos>
          <profile>
            <entry name="default">
              <class-bandwidth-type>
                <mbps>
                  <class>
                    <entry name="class1">
                      <priority>real-time</priority>
                    </entry>
                    <entry name="class2">
                      <priority>high</priority>
                    </entry>
                    <entry name="class3">
                      <priority>high</priority>
                    </entry>
                    <entry name="class4">
                      <priority>medium</priority>
                    </entry>
                    <entry name="class5">
                      <priority>medium</priority>
                    </entry>
                    <entry name="class6">
                      <priority>low</priority>
                    </entry>
                    <entry name="class7">
                      <priority>low</priority>
                    </entry>
                    <entry name="class8">
                      <priority>low</priority>
                    </entry>
                  </class>
                </mbps>
              </class-bandwidth-type>
            </entry>
          </profile>
        </qos>
        <virtual-router>
          <entry name="lab-vr">
            <protocol>
              <bgp>
                <enable>no</enable>
                <dampening-profile>
                  <entry name="default">
                    <cutoff>1.25</cutoff>
                    <reuse>0.5</reuse>
                    <max-hold-time>900</max-hold-time>
                    <decay-half-life-reachable>300</decay-half-life-reachable>
                    <decay-half-life-unreachable>900</decay-half-life-unreachable>
                    <enable>yes</enable>
                  </entry>
                </dampening-profile>
                <routing-options>
                  <graceful-restart>
                    <enable>yes</enable>
                  </graceful-restart>
                </routing-options>
              </bgp>
              <rip>
                <enable>no</enable>
              </rip>
              <ospf>
                <enable>no</enable>
              </ospf>
              <ospfv3>
                <enable>no</enable>
              </ospfv3>
            </protocol>
            <ecmp>
              <algorithm>
                <ip-modulo/>
              </algorithm>
            </ecmp>
            <routing-table>
              <ip>
                <static-route>
                  <entry name="default-route">
                    <nexthop>
                      <ip-address>203.0.113.1</ip-address>
                    </nexthop>
                    <bfd>
                      <profile>None</profile>
                    </bfd>
                    <path-monitor>
                      <enable>no</enable>
                      <failure-condition>any</failure-condition>
                      <hold-time>2</hold-time>
                    </path-monitor>
                    <interface>ethernet1/1</interface>
                    <metric>10</metric>
                    <destination>0.0.0.0/0</destination>
                    <route-table>
                      <unicast/>
                    </route-table>
                  </entry>
                  <entry name="to-tunnel">
                    <path-monitor>
                      <enable>no</enable>
                      <failure-condition>any</failure-condition>
                      <hold-time>2</hold-time>
                    </path-monitor>
                    <bfd>
                      <profile>None</profile>
                    </bfd>
                    <interface>tunnel.12</interface>
                    <metric>10</metric>
                    <destination>172.16.2.0/24</destination>
                    <route-table>
                      <unicast/>
                    </route-table>
                  </entry>
                </static-route>
              </ip>
            </routing-table>
            <interface>
              <member>ethernet1/1</member>
              <member>ethernet1/2</member>
              <member>ethernet1/2.2</member>
              <member>ethernet1/3</member>
              <member>tunnel.11</member>
              <member>tunnel.12</member>
            </interface>
          </entry>
        </virtual-router>
        <virtual-wire>
          <entry name="danger">
            <interface1>ethernet1/4</interface1>
            <interface2>ethernet1/5</interface2>
            <link-state-pass-through>
              <enable>no</enable>
            </link-state-pass-through>
          </entry>
        </virtual-wire>
        <tunnel>
          <global-protect-gateway/>
          <ipsec>
            <entry name="extranet-tunnel">
              <auto-key>
                <ike-gateway>
                  <entry name="extranet-ike-gateway"/>
                </ike-gateway>
                <proxy-id>
                  <entry name="extranet-tunnel-network">
                    <protocol>
                      <any/>
                    </protocol>
                    <local>192.168.2.0/24</local>
                    <remote>172.16.2.0/24</remote>
                  </entry>
                </proxy-id>
                <ipsec-crypto-profile>AES256-SHA256</ipsec-crypto-profile>
              </auto-key>
              <tunnel-monitor>
                <enable>no</enable>
                <destination-ip>172.16.2.11</destination-ip>
              </tunnel-monitor>
              <tunnel-interface>tunnel.12</tunnel-interface>
            </entry>
          </ipsec>
        </tunnel>
        <dns-proxy>
          <entry name="gp-dns-proxy">
            <cache>
              <max-ttl>
                <enabled>no</enabled>
              </max-ttl>
              <enabled>yes</enabled>
            </cache>
            <default>
              <primary>4.2.2.2</primary>
              <secondary>8.8.8.8</secondary>
            </default>
            <tcp-queries>
              <enabled>no</enabled>
            </tcp-queries>
            <static-entries>
              <entry name="Internal Host Detection">
                <address>
                  <member>192.168.2.1</member>
                </address>
                <domain>gp-int-gw-lab.local</domain>
              </entry>
            </static-entries>
            <interface>
              <member>ethernet1/2</member>
            </interface>
          </entry>
        </dns-proxy>
      </network>
      <deviceconfig>
        <system>
          <type>
            <static/>
          </type>
          <update-server>updates.paloaltonetworks.com</update-server>
          <update-schedule>
            <threats>
              <recurring>
                <weekly>
                  <day-of-week>wednesday</day-of-week>
                  <at>01:05</at>
                  <action>download-only</action>
                </weekly>
              </recurring>
            </threats>
            <anti-virus>
              <recurring>
                <daily>
                  <at>01:02</at>
                  <action>download-and-install</action>
                </daily>
              </recurring>
            </anti-virus>
            <wildfire>
              <recurring>
                <every-min>
                  <action>download-and-install</action>
                </every-min>
              </recurring>
            </wildfire>
          </update-schedule>
          <timezone>Etc/UTC</timezone>
          <service>
            <disable-telnet>yes</disable-telnet>
            <disable-http>yes</disable-http>
          </service>
          <hostname>firewall-a</hostname>
          <ip-address>192.168.1.254</ip-address>
          <netmask>255.255.255.0</netmask>
          <default-gateway>192.168.1.1</default-gateway>
          <dns-setting>
            <servers>
              <primary>8.8.8.8</primary>
              <secondary>1.1.1.1</secondary>
            </servers>
          </dns-setting>
          <domain>panw.lab</domain>
          <ntp-servers>
            <primary-ntp-server>
              <ntp-server-address>192.168.1.20</ntp-server-address>
              <authentication-type>
                <none/>
              </authentication-type>
            </primary-ntp-server>
          </ntp-servers>
          <device-telemetry>
            <device-health-performance>yes</device-health-performance>
            <product-usage>yes</product-usage>
            <threat-prevention>yes</threat-prevention>
          </device-telemetry>
        </system>
        <setting>
          <config>
            <rematch>yes</rematch>
          </config>
          <management>
            <hostname-type-in-syslog>FQDN</hostname-type-in-syslog>
            <idle-timeout>0</idle-timeout>
          </management>
          <auto-mac-detect>yes</auto-mac-detect>
          <application>
            <notify-user>yes</notify-user>
          </application>
          <tcp>
            <drop-zero-flag>yes</drop-zero-flag>
            <check-timestamp-option>yes</check-timestamp-option>
          </tcp>
        </setting>
      </deviceconfig>
      <vsys>
        <entry name="vsys1">
          <application/>
          <application-group/>
          <zone>
            <entry name="outside">
              <network>
                <layer3>
                  <member>ethernet1/1</member>
                </layer3>
              </network>
            </entry>
            <entry name="inside">
              <network>
                <layer3>
                  <member>ethernet1/2</member>
                  <member>ethernet1/2.2</member>
                  <member>tunnel.11</member>
                </layer3>
              </network>
              <enable-user-identification>yes</enable-user-identification>
            </entry>
            <entry name="extranet">
              <network>
                <layer3>
                  <member>ethernet1/3</member>
                </layer3>
              </network>
            </entry>
            <entry name="danger">
              <network>
                <virtual-wire>
                  <member>ethernet1/4</member>
                  <member>ethernet1/5</member>
                </virtual-wire>
              </network>
              <enable-user-identification>yes</enable-user-identification>
            </entry>
            <entry name="vpn-12">
              <network>
                <layer3>
                  <member>tunnel.12</member>
                </layer3>
              </network>
            </entry>
          </zone>
          <service>
            <entry name="service-ftp">
              <protocol>
                <tcp>
                  <port>20-21</port>
                </tcp>
              </protocol>
            </entry>
          </service>
          <service-group/>
          <schedule/>
          <rulebase>
            <nat>
              <rules>
                <entry name="gp-portal-no-nat" uuid="ce4a57be-6c81-4c68-b5b8-b8beb8fd81a9">
                  <to>
                    <member>outside</member>
                  </to>
                  <from>
                    <member>inside</member>
                  </from>
                  <source>
                    <member>any</member>
                  </source>
                  <destination>
                    <member>203.0.113.20</member>
                  </destination>
                  <tag>
                    <member>internal</member>
                  </tag>
                  <service>any</service>
                  <to-interface>ethernet1/1</to-interface>
                  <group-tag>internal</group-tag>
                </entry>
                <entry name="source-egress-outside" uuid="d67c4e80-0036-4607-9281-639248249638">
                  <source-translation>
                    <dynamic-ip-and-port>
                      <interface-address>
                        <ip>203.0.113.20/24</ip>
                        <interface>ethernet1/1</interface>
                      </interface-address>
                    </dynamic-ip-and-port>
                  </source-translation>
                  <to>
                    <member>outside</member>
                  </to>
                  <from>
                    <member>extranet</member>
                    <member>inside</member>
                  </from>
                  <source>
                    <member>any</member>
                  </source>
                  <destination>
                    <member>any</member>
                  </destination>
                  <tag>
                    <member>egress</member>
                  </tag>
                  <service>any</service>
                  <to-interface>ethernet1/1</to-interface>
                  <group-tag>egress</group-tag>
                </entry>
              </rules>
            </nat>
            <security>
              <rules>
                <entry name="inside-to-extranet" uuid="68f2bcb6-150d-47c8-8f19-9fd9c684359d">
                  <to>
                    <member>extranet</member>
                  </to>
                  <from>
                    <member>inside</member>
                  </from>
                  <source>
                    <member>any</member>
                  </source>
                  <destination>
                    <member>any</member>
                  </destination>
                  <source-user>
                    <member>any</member>
                  </source-user>
                  <category>
                    <member>any</member>
                  </category>
                  <application>
                    <member>any</member>
                  </application>
                  <service>
                    <member>application-default</member>
                  </service>
                  <action>allow</action>
                  <disabled>no</disabled>
                  <group-tag>egress</group-tag>
                  <source-hip>
                    <member>any</member>
                  </source-hip>
                </entry>
                <entry name="extranet-to-inside" uuid="4f1fe66b-d777-40fd-834c-be589ab185b9">
                  <to>
                    <member>inside</member>
                  </to>
                  <from>
                    <member>extranet</member>
                  </from>
                  <source>
                    <member>any</member>
                  </source>
                  <destination>
                    <member>any</member>
                  </destination>
                  <source-user>
                    <member>any</member>
                  </source-user>
                  <category>
                    <member>any</member>
                  </category>
                  <application>
                    <member>any</member>
                  </application>
                  <service>
                    <member>application-default</member>
                  </service>
                  <action>allow</action>
                  <source-hip>
                    <member>any</member>
                  </source-hip>
                </entry>
                <entry name="inside-to-vpn" uuid="1476814c-cb55-4377-81d9-f31f72dc539b">
                  <to>
                    <member>vpn-12</member>
                  </to>
                  <from>
                    <member>inside</member>
                  </from>
                  <source>
                    <member>any</member>
                  </source>
                  <destination>
                    <member>any</member>
                  </destination>
                  <source-user>
                    <member>any</member>
                  </source-user>
                  <category>
                    <member>any</member>
                  </category>
                  <application>
                    <member>any</member>
                  </application>
                  <service>
                    <member>application-default</member>
                  </service>
                  <action>allow</action>
                  <source-hip>
                    <member>any</member>
                  </source-hip>
                </entry>
                <entry name="vpn-to-inside" uuid="e9ccae10-4dcd-4e37-bbaf-6bc442b90e68">
                  <to>
                    <member>inside</member>
                  </to>
                  <from>
                    <member>vpn-12</member>
                  </from>
                  <source>
                    <member>any</member>
                  </source>
                  <destination>
                    <member>any</member>
                  </destination>
                  <source-user>
                    <member>any</member>
                  </source-user>
                  <category>
                    <member>any</member>
                  </category>
                  <application>
                    <member>any</member>
                  </application>
                  <service>
                    <member>application-default</member>
                  </service>
                  <action>allow</action>
                  <rule-type>universal</rule-type>
                  <source-hip>
                    <member>any</member>
                  </source-hip>
                </entry>
                <entry name="dns-no-log" uuid="0248d211-c003-4800-853d-ea98b1f5a4ec">
                  <to>
                    <member>outside</member>
                  </to>
                  <from>
                    <member>inside</member>
                  </from>
                  <source>
                    <member>any</member>
                  </source>
                  <destination>
                    <member>any</member>
                  </destination>
                  <source-user>
                    <member>any</member>
                  </source-user>
                  <category>
                    <member>any</member>
                  </category>
                  <application>
                    <member>dns</member>
                  </application>
                  <service>
                    <member>application-default</member>
                  </service>
                  <action>allow</action>
                  <disabled>no</disabled>
                  <group-tag>egress</group-tag>
                  <log-end>no</log-end>
                  <tag>
                    <member>no-log</member>
                  </tag>
                  <source-hip>
                    <member>any</member>
                  </source-hip>
                </entry>
                <entry name="inside-to-internet" uuid="5908d3c2-ed46-41c4-9e62-d29f71def3fa">
                  <to>
                    <member>outside</member>
                  </to>
                  <from>
                    <member>inside</member>
                  </from>
                  <source>
                    <member>any</member>
                  </source>
                  <destination>
                    <member>any</member>
                  </destination>
                  <source-user>
                    <member>any</member>
                  </source-user>
                  <category>
                    <member>any</member>
                  </category>
                  <application>
                    <member>any</member>
                  </application>
                  <service>
                    <member>application-default</member>
                  </service>
                  <action>allow</action>
                  <disabled>no</disabled>
                  <group-tag>egress</group-tag>
                  <source-hip>
                    <member>any</member>
                  </source-hip>
                </entry>
                <entry name="extranet-to-outside" uuid="2821f754-6b4b-487a-baaa-adee29516e3e">
                  <to>
                    <member>outside</member>
                  </to>
                  <from>
                    <member>extranet</member>
                  </from>
                  <source>
                    <member>any</member>
                  </source>
                  <destination>
                    <member>any</member>
                  </destination>
                  <source-user>
                    <member>any</member>
                  </source-user>
                  <category>
                    <member>any</member>
                  </category>
                  <application>
                    <member>any</member>
                  </application>
                  <service>
                    <member>application-default</member>
                  </service>
                  <action>allow</action>
                  <source-hip>
                    <member>any</member>
                  </source-hip>
                </entry>
                <entry name="danger-simulated-traffic" uuid="5d5192fa-1661-45c6-aaa8-98d448c29595">
                  <profile-setting>
                    <group>
                      <member>lab-spg</member>
                    </group>
                  </profile-setting>
                  <to>
                    <member>danger</member>
                  </to>
                  <from>
                    <member>danger</member>
                  </from>
                  <source>
                    <member>any</member>
                  </source>
                  <destination>
                    <member>any</member>
                  </destination>
                  <source-user>
                    <member>any</member>
                  </source-user>
                  <category>
                    <member>any</member>
                  </category>
                  <application>
                    <member>any</member>
                  </application>
                  <service>
                    <member>application-default</member>
                  </service>
                  <tag/>
                  <action>allow</action>
                  <log-start>no</log-start>
                  <disabled>yes</disabled>
                  <source-hip>
                    <member>any</member>
                  </source-hip>
                </entry>
              </rules>
            </security>
            <default-security-rules>
              <rules>
                <entry name="interzone-default" uuid="85dc568f-e240-44f8-a72b-36f19a2c74fd">
                  <action>deny</action>
                  <log-start>no</log-start>
                  <log-end>yes</log-end>
                </entry>
              </rules>
            </default-security-rules>
          </rulebase>
          <import>
            <network>
              <interface>
                <member>ethernet1/2</member>
                <member>ethernet1/3</member>
                <member>ethernet1/1</member>
                <member>ethernet1/4</member>
                <member>ethernet1/5</member>
                <member>ethernet1/2.2</member>
                <member>tunnel.11</member>
                <member>tunnel.12</member>
              </interface>
            </network>
          </import>
          <tag>
            <entry name="danger">
              <color>color5</color>
            </entry>
            <entry name="egress">
              <color>color4</color>
            </entry>
            <entry name="extranet">
              <color>color3</color>
            </entry>
            <entry name="internal">
              <color>color22</color>
            </entry>
            <entry name="inside">
              <color>color9</color>
            </entry>
            <entry name="outside">
              <color>color42</color>
            </entry>
            <entry name="no-log">
              <color>color11</color>
            </entry>
            <entry name="vpn-12">
              <color>color10</color>
            </entry>
          </tag>
          <profiles>
            <virus>
              <entry name="lab-av">
                <decoder>
                  <entry name="smtp">
                    <action>default</action>
                    <wildfire-action>default</wildfire-action>
                    <mlav-action>default</mlav-action>
                  </entry>
                  <entry name="smb">
                    <action>default</action>
                    <wildfire-action>default</wildfire-action>
                    <mlav-action>default</mlav-action>
                  </entry>
                  <entry name="pop3">
                    <action>default</action>
                    <wildfire-action>default</wildfire-action>
                    <mlav-action>default</mlav-action>
                  </entry>
                  <entry name="imap">
                    <action>default</action>
                    <wildfire-action>default</wildfire-action>
                    <mlav-action>default</mlav-action>
                  </entry>
                  <entry name="http">
                    <action>reset-server</action>
                    <wildfire-action>default</wildfire-action>
                    <mlav-action>reset-server</mlav-action>
                  </entry>
                  <entry name="ftp">
                    <action>default</action>
                    <wildfire-action>default</wildfire-action>
                    <mlav-action>default</mlav-action>
                  </entry>
                </decoder>
                <packet-capture>yes</packet-capture>
              </entry>
            </virus>
            <spyware>
              <entry name="lab-as">
                <botnet-domains>
                  <lists>
                    <entry name="default-paloalto-dns">
                      <action>
                        <sinkhole/>
                      </action>
                    </entry>
                    <entry name="lab-dns-sinkhole">
                      <action>
                        <sinkhole/>
                      </action>
                    </entry>
                  </lists>
                  <sinkhole>
                    <ipv4-address>pan-sinkhole-default-ip</ipv4-address>
                    <ipv6-address>::1</ipv6-address>
                  </sinkhole>
                </botnet-domains>
                <rules>
                  <entry name="med-low-info">
                    <action>
                      <alert/>
                    </action>
                    <severity>
                      <member>medium</member>
                      <member>low</member>
                      <member>informational</member>
                    </severity>
                    <threat-name>any</threat-name>
                    <category>any</category>
                    <packet-capture>disable</packet-capture>
                  </entry>
                  <entry name="crit-high">
                    <action>
                      <alert/>
                    </action>
                    <severity>
                      <member>high</member>
                      <member>critical</member>
                    </severity>
                    <threat-name>any</threat-name>
                    <category>any</category>
                    <packet-capture>disable</packet-capture>
                  </entry>
                </rules>
              </entry>
            </spyware>
            <vulnerability>
              <entry name="lab-vp">
                <rules>
                  <entry name="lab-vp-rule">
                    <action>
                      <reset-both/>
                    </action>
                    <vendor-id>
                      <member>any</member>
                    </vendor-id>
                    <severity>
                      <member>high</member>
                    </severity>
                    <cve>
                      <member>any</member>
                    </cve>
                    <threat-name>any</threat-name>
                    <host>any</host>
                    <category>any</category>
                    <packet-capture>single-packet</packet-capture>
                  </entry>
                </rules>
              </entry>
            </vulnerability>
            <file-blocking>
              <entry name="lab-file-blocking">
                <rules>
                  <entry name="block-pdf">
                    <application>
                      <member>any</member>
                    </application>
                    <file-type>
                      <member>any</member>
                    </file-type>
                    <direction>both</direction>
                    <action>block</action>
                  </entry>
                </rules>
              </entry>
            </file-blocking>
            <custom-url-category>
              <entry name="tech-sites">
                <list>
                  <member>newegg.com</member>
                  <member>engadget.com</member>
                  <member>techradar.com</member>
                  <member>*.newegg.com</member>
                  <member>*.engadget.com</member>
                  <member>*.techradar.com</member>
                </list>
                <type>URL List</type>
              </entry>
            </custom-url-category>
            <url-filtering>
              <entry name="lab-url-filtering">
                <credential-enforcement>
                  <mode>
                    <disabled/>
                  </mode>
                  <log-severity>medium</log-severity>
                  <allow>
                    <member>url-block-list</member>
                    <member>tech-sites</member>
                  </allow>
                  <block>
                    <member>government</member>
                    <member>hacking</member>
                    <member>shopping</member>
                  </block>
                </credential-enforcement>
                <allow>
                  <member>url-block-list</member>
                  <member>tech-sites</member>
                </allow>
                <block>
                  <member>government</member>
                  <member>hacking</member>
                  <member>shopping</member>
                </block>
              </entry>
            </url-filtering>
            <wildfire-analysis>
              <entry name="lab-wildfire">
                <rules>
                  <entry name="pe">
                    <application>
                      <member>any</member>
                    </application>
                    <file-type>
                      <member>pe</member>
                    </file-type>
                    <direction>both</direction>
                    <analysis>public-cloud</analysis>
                  </entry>
                </rules>
              </entry>
            </wildfire-analysis>
          </profiles>
          <external-list>
            <entry name="lab-dns-sinkhole">
              <type>
                <domain>
                  <recurring>
                    <five-minute/>
                  </recurring>
                  <url>http://192.168.50.10/dns-sinkhole.txt</url>
                </domain>
              </type>
            </entry>
            <entry name="url-block-list">
              <type>
                <url>
                  <recurring>
                    <five-minute/>
                  </recurring>
                  <url>http://192.168.50.10/block-list.txt</url>
                </url>
              </type>
            </entry>
          </external-list>
          <profile-group>
            <entry name="lab-spg">
              <virus>
                <member>lab-av</member>
              </virus>
              <spyware>
                <member>lab-as</member>
              </spyware>
              <vulnerability>
                <member>lab-vp</member>
              </vulnerability>
              <url-filtering>
                <member>lab-url-filtering</member>
              </url-filtering>
              <wildfire-analysis>
                <member>lab-wildfire</member>
              </wildfire-analysis>
            </entry>
          </profile-group>
          <global-protect>
            <global-protect-gateway/>
            <global-protect-portal/>
          </global-protect>
          <user-id-collector>
            <setting/>
          </user-id-collector>
        </entry>
      </vsys>
    </entry>
  </devices>
</config>
